feltools/__init__.py
feltools/_internal/__init__.py
feltools/_internal/err.py
feltools/_internal/funcs.py
feltools-0.0.4.dist-info/METADATA
feltools-0.0.4.dist-info/WHEEL
feltools-0.0.4.dist-info/top_level.txt
feltools-0.0.4.dist-info/RECORD
