Metadata-Version: 2.2
Name: feltools
Version: 0.0.4
Summary: A collection of simple tools in Python
Home-page: 
Author: Felix Reiter
Author-email: sbody1113@gmail.com
Dynamic: author
Dynamic: author-email
Dynamic: description
Dynamic: description-content-type
Dynamic: summary
